koila/__init__.py
koila/constants.py
koila/eager.py
koila/errors.py
koila/gpus.py
koila/interfaces.py
koila/lazy.py
koila/prepasses.py
koila/shapes.py
koila-0.1.1.dist-info/LICENCE
koila-0.1.1.dist-info/METADATA
koila-0.1.1.dist-info/WHEEL
koila-0.1.1.dist-info/top_level.txt
koila-0.1.1.dist-info/RECORD
