Metadata-Version: 2.1
Name: koila
Version: 0.1.1
Summary: Prevent PyTorch's `CUDA error: out of memory` in one line of code.
Home-page: UNKNOWN
Author: RenChu Wang
License: UNKNOWN
Platform: UNKNOWN
Classifier: Programming Language :: Python :: 3
Classifier: Programming Language :: Python :: 3.8
Classifier: Programming Language :: Python :: 3.9
Classifier: License :: OSI Approved :: MIT License
Classifier: Operating System :: OS Independent
Requires-Python: >=3.8
Requires-Dist: numpy
Requires-Dist: pynvml
Requires-Dist: rich
Requires-Dist: torch
